Metadata-Version: 2.1
Name: alibabacloud-darabonba-encode-util
Version: 0.0.1
Summary: Darabonba Util Library for Alibaba Cloud Python SDK
Home-page: https://github.com/aliyun/darabonba-crypto-util
Author: Alibaba Cloud SDK
Author-email: sdk-darabonbam@alibabacloud.com
License: Apache License 2.0
Keywords: alibabacloud,darabonba,encode,util
Platform: any
Classifier: Development Status :: 4 - Beta
Classifier: Intended Audience :: Developers
Classifier: License :: OSI Approved :: Apache Software License
Classifier: Programming Language :: Python
Classifier: Programming Language :: Python :: 3
Classifier: Programming Language :: Python :: 3.6
Classifier: Programming Language :: Python :: 3.7
Classifier: Programming Language :: Python :: 3.8
Classifier: Programming Language :: Python :: 3.9
Classifier: Topic :: Software Development
Requires-Python: >=3.6
